windkit/__init__.py
windkit/_errors.py
windkit/_rvea_xml.py
windkit/_version.py
windkit/_weibull_nb.py
windkit/cfd.py
windkit/config.py
windkit/import_manager.py
windkit/tutorial_data.py
windkit/utils.py
windkit/weibull.py
windkit/weng_workspace.py
windkit/wind.py
windkit/wind_data.py
windkit/workspace.py
windkit/data/all_vars.json
windkit/data/color_table_roughness.json
windkit/data/map_file_header_to_epsg.json
windkit/data/map_file_header_to_epsg_read.json
windkit/data/landcover_tables/CGLS-LC100.json
windkit/data/landcover_tables/CORINE.json
windkit/data/landcover_tables/ESA_CCI.json
windkit/data/landcover_tables/GWA4_micro.json
windkit/data/landcover_tables/Globcover.json
windkit/data/landcover_tables/MODIS.json
windkit/data/landcover_tables/NEWA_micro_v2.json
windkit/data/landcover_tables/WorldCover.json
windkit/data/loss_tables/dtu_loss_table.csv
windkit/data/uncertainty_tables/dtu_uncertainty_table.csv
windkit/integrations/__init__.py
windkit/integrations/_earth_engine.py
windkit/integrations/_gwa_map_api.py
windkit/integrations/_planetary_computer.py
windkit/ltc/__init__.py
windkit/ltc/_validation.py
windkit/ltc/mcp.py
windkit/ltc/regression.py
windkit/ltc/scores.py
windkit/plot/__init__.py
windkit/plot/_colormaps.py
windkit/plot/_helpers.py
windkit/plot/color.py
windkit/plot/elevation_map.py
windkit/plot/histogram.py
windkit/plot/landcover_map.py
windkit/plot/operational_curves.py
windkit/plot/raster_plot.py
windkit/plot/roughness_rose.py
windkit/plot/time_series.py
windkit/plot/vertical_profile.py
windkit/plot/wind_rose.py
windkit/plot/wind_turbine.py
windkit/spatial/README.md
windkit/spatial/__init__.py
windkit/spatial/_bbox.py
windkit/spatial/_conversions.py
windkit/spatial/_crs.py
windkit/spatial/_cuboid.py
windkit/spatial/_dimensions.py
windkit/spatial/_interpolation.py
windkit/spatial/_latitude.py
windkit/spatial/_metpy_natural_neighbors.py
windkit/spatial/_point.py
windkit/spatial/_raster.py
windkit/spatial/_struct.py
windkit/spatial/_utm.py
windkit-2.0.1.dist-info/licenses/LICENSE
windkit-2.0.1.dist-info/METADATA
windkit-2.0.1.dist-info/WHEEL
windkit-2.0.1.dist-info/entry_points.txt
windkit-2.0.1.dist-info/top_level.txt
windkit-2.0.1.dist-info/RECORD
