Metadata-Version: 2.4
Name: windkit
Version: 2.0.1
Summary: WindKit provides core functionalities for working with wind resource data
Author: DTU Wind Energy
License-Expression: BSD-3-Clause
Classifier: Programming Language :: Python :: 3
Classifier: Operating System :: OS Independent
Requires-Python: >=3.11
License-File: LICENSE
Requires-Dist: geopandas>=1.0
Requires-Dist: h5netcdf
Requires-Dist: lxml>=5.0
Requires-Dist: netcdf4>=1.6
Requires-Dist: numpy>=1.26
Requires-Dist: packaging>=23
Requires-Dist: pandas>=2.1
Requires-Dist: platformdirs>=4.3
Requires-Dist: pydantic>=2.7
Requires-Dist: pydantic-settings>=2.3
Requires-Dist: pyproj>=3.6
Requires-Dist: pyyaml
Requires-Dist: rasterio>=1.3
Requires-Dist: requests
Requires-Dist: rioxarray>=0.17
Requires-Dist: scipy>=1.12
Requires-Dist: shapely>=2.0
Requires-Dist: toml
Requires-Dist: xarray>=2023.9
Provides-Extra: plots
Requires-Dist: matplotlib>=3.8; extra == "plots"
Requires-Dist: plotly>=5.12.0; extra == "plots"
Requires-Dist: kaleido; extra == "plots"
Provides-Extra: performance
Requires-Dist: numba>=0.57.0; extra == "performance"
Provides-Extra: data-apis
Requires-Dist: adlfs; extra == "data-apis"
Requires-Dist: earthengine-api; extra == "data-apis"
Requires-Dist: fsspec; extra == "data-apis"
Requires-Dist: planetary-computer; extra == "data-apis"
Requires-Dist: pystac-client; extra == "data-apis"
Requires-Dist: zarr>2.15; extra == "data-apis"
Provides-Extra: dev
Requires-Dist: dash; extra == "dev"
Requires-Dist: ipython; extra == "dev"
Requires-Dist: nbval; extra == "dev"
Requires-Dist: pre-commit; extra == "dev"
Requires-Dist: pytest; extra == "dev"
Requires-Dist: pytest-cov; extra == "dev"
Requires-Dist: pytest-xdist; extra == "dev"
Requires-Dist: windIO; extra == "dev"
Provides-Extra: doc
Requires-Dist: docutils; extra == "doc"
Requires-Dist: jupyter; extra == "doc"
Requires-Dist: jupyter-dash; extra == "doc"
Requires-Dist: jupyter-sphinx; extra == "doc"
Requires-Dist: myst-parser; extra == "doc"
Requires-Dist: nbsphinx; extra == "doc"
Requires-Dist: nbsphinx-link; extra == "doc"
Requires-Dist: pydata-sphinx-theme; extra == "doc"
Requires-Dist: recommonmark; extra == "doc"
Requires-Dist: sphinx; extra == "doc"
Requires-Dist: sphinx-argparse; extra == "doc"
Requires-Dist: sphinx-copybutton; extra == "doc"
Requires-Dist: sphinx-design; extra == "doc"
Requires-Dist: sphinx-gallery; extra == "doc"
Requires-Dist: sphinxcontrib-bibtex; extra == "doc"
Requires-Dist: sphinxext-opengraph; extra == "doc"
Dynamic: license-file
